shelltool.py
shelltool-0.1.2.dist-info/LICENSE
shelltool-0.1.2.dist-info/METADATA
shelltool-0.1.2.dist-info/WHEEL
shelltool-0.1.2.dist-info/top_level.txt
shelltool-0.1.2.dist-info/RECORD
