Metadata-Version: 2.1
Name: shelltool
Version: 0.1.2
Summary: A better way to compose shell-like commands in python.
Author: William L.
Project-URL: Homepage, https://github.com/FrewtyPebbles/Shellify.py
Project-URL: Issues, https://github.com/FrewtyPebbles/Shellify.py/issues
Classifier: Programming Language :: Python :: 3
Classifier: License :: OSI Approved :: MIT License
Classifier: Operating System :: OS Independent
Requires-Python: >=3.10
License-File: LICENSE
